datau/__init__.py
datau/__main__.py
datau/datau.py
pydatau-1.0.8.dist-info/licenses/LICENSE
pydatau-1.0.8.dist-info/METADATA
pydatau-1.0.8.dist-info/WHEEL
pydatau-1.0.8.dist-info/entry_points.txt
pydatau-1.0.8.dist-info/top_level.txt
pydatau-1.0.8.dist-info/RECORD
