Metadata-Version: 2.4
Name: pydatau
Version: 1.0.8
Summary: Batch Statistical Data Utilities
Author-email: The Economist <29724411+econcz@users.noreply.github.com>
License-Expression: MIT
Project-URL: Homepage, https://github.com/econcz/pydatau
Project-URL: Bug Tracker, https://github.com/econcz/pydatau/issues
Keywords: data-science,ipython,R,stata,gams,ampl,matlab,octave
Classifier: Programming Language :: Python :: 3
Classifier: Programming Language :: Python :: 3.10
Classifier: Programming Language :: Python :: 3.11
Classifier: Programming Language :: Python :: 3.12
Classifier: Operating System :: OS Independent
Classifier: Topic :: Scientific/Engineering :: Information Analysis
Requires-Python: >=3.10
License-File: LICENSE
Requires-Dist: papermill
Requires-Dist: rpy2
Requires-Dist: stata_kernel
Requires-Dist: oct2py
Provides-Extra: matlab
Requires-Dist: matlabengineforpython; extra == "matlab"
Dynamic: license-file
